{
  "lastUpdated": "2026-03-05T13:00:07.675357+00:00",
  "positions": [
    {
      "trade_id": "ALF-d453b65c",
      "bot_id": "alfred",
      "ticker": "COIN",
      "side": "BUY",
      "quantity": 10.0,
      "entry_price": 210.49,
      "market": "US",
      "status": "OPEN",
      "current_price": 208.93,
      "unrealized_pl": -15.6,
      "unrealized_pl_pct": -0.74
    },
    {
      "trade_id": "ACR-ba1d9bc2",
      "bot_id": "alfred",
      "ticker": "BTC-USD",
      "side": "BUY",
      "quantity": 0.0918,
      "entry_price": 73405.0,
      "market": "CRYPTO",
      "status": "OPEN",
      "current_price": null,
      "price_status": "stale",
      "unrealized_pl": null,
      "unrealized_pl_pct": null
    },
    {
      "trade_id": "ALFRED_CRYPTO-8c6895a1",
      "bot_id": "alfred_crypto",
      "ticker": "RENDER-USD",
      "side": "BUY",
      "quantity": 2193.0,
      "entry_price": 1.45,
      "market": "CRYPTO",
      "status": "OPEN",
      "current_price": null,
      "price_status": "stale",
      "unrealized_pl": null,
      "unrealized_pl_pct": null
    },
    {
      "trade_id": "ALFRED_CRYPTO-73bad0a3",
      "bot_id": "alfred_crypto",
      "ticker": "ETH-USD",
      "side": "BUY",
      "quantity": 0.97,
      "entry_price": 2186.0,
      "market": "CRYPTO",
      "status": "OPEN",
      "current_price": null,
      "price_status": "stale",
      "unrealized_pl": null,
      "unrealized_pl_pct": null
    },
    {
      "trade_id": "ALFRED_CRYPTO-43354a4f",
      "bot_id": "alfred_crypto",
      "ticker": "SOL-USD",
      "side": "BUY",
      "quantity": 3.2,
      "entry_price": 92.75,
      "market": "CRYPTO",
      "status": "OPEN",
      "current_price": null,
      "price_status": "stale",
      "unrealized_pl": null,
      "unrealized_pl_pct": null
    },
    {
      "trade_id": "ALFRED_CRYPTO-047e3507",
      "bot_id": "alfred_crypto",
      "ticker": "ETH-USD",
      "side": "BUY",
      "quantity": 3.18,
      "entry_price": 2200.0,
      "market": "CRYPTO",
      "status": "OPEN",
      "current_price": null,
      "price_status": "stale",
      "unrealized_pl": null,
      "unrealized_pl_pct": null
    },
    {
      "trade_id": "ALFRED_CRYPTO-647ec139",
      "bot_id": "alfred_crypto",
      "ticker": "BTC-USD",
      "side": "BUY",
      "quantity": 0.115,
      "entry_price": 69200.0,
      "market": "CRYPTO",
      "status": "OPEN",
      "current_price": null,
      "price_status": "stale",
      "unrealized_pl": null,
      "unrealized_pl_pct": null
    },
    {
      "trade_id": "ACR-47c1dfc6",
      "bot_id": "alfred_crypto",
      "ticker": "LINK-USD",
      "side": "BUY",
      "quantity": 250.0,
      "entry_price": 9.48,
      "market": "CRYPTO",
      "status": "OPEN",
      "current_price": null,
      "price_status": "stale",
      "unrealized_pl": null,
      "unrealized_pl_pct": null
    }
  ],
  "signals": [],
  "pendingOrders": [],
  "cashBalance": null,
  "summary": {
    "total_positions": 8,
    "priced": 1,
    "stale": 7,
    "total_unrealized_pl": -15.6
  },
  "notes": "Synced 8 positions (1 priced, 7 stale). Total unrealized P&L: $-15.60"
}